{
    "dependent_repos_count": 26,
    "dependents_count": 18,
    "deprecation_reason": null,
    "description": "'GitHub' 'API'",
    "forks": 43,
    "homepage": "https://gh.r-lib.org/",
    "keywords": [
        "github",
        "github-api",
        "r"
    ],
    "language": "R",
    "latest_download_url": "https://cran.r-project.org/src/contrib/gh_1.3.0.tar.gz",
    "latest_release_number": "1.3.0",
    "latest_release_published_at": "2021-04-30T00:00:00.000Z",
    "latest_stable_release_number": "1.3.0",
    "latest_stable_release_published_at": "2021-04-30T00:00:00.000Z",
    "license_normalized": true,
    "licenses": "MIT + file LICENSE",
    "name": "gh",
    "normalized_licenses": [
        "MIT"
    ],
    "package_manager_url": "https://cran.r-project.org/package=gh",
    "platform": "CRAN",
    "rank": 15,
    "repository_license": "Other",
    "repository_url": "",
    "stars": 156,
    "status": null,
    "versions": [
        {
            "number": "1.0.1",
            "published_at": "2017-07-16T22:28:00.000Z",
            "spdx_expression": null,
            "original_license": null,
            "researched_at": null,
            "repository_sources": [
                "CRAN"
            ]
        },
        {
            "number": "1.1.0",
            "published_at": "2020-01-24T07:50:00.000Z",
            "spdx_expression": null,
            "original_license": null,
            "researched_at": null,
            "repository_sources": [
                "CRAN"
            ]
        },
        {
            "number": "1.2.0",
            "published_at": "2020-11-27T14:50:00.000Z",
            "spdx_expression": null,
            "original_license": null,
            "researched_at": null,
            "repository_sources": [
                "CRAN"
            ]
        },
        {
            "number": "1.2.1",
            "published_at": "2021-04-01T23:10:00.000Z",
            "spdx_expression": null,
            "original_license": null,
            "researched_at": null,
            "repository_sources": [
                "CRAN"
            ]
        },
        {
            "number": "1.3.0",
            "published_at": "2021-04-30T00:00:00.000Z",
            "spdx_expression": null,
            "original_license": null,
            "researched_at": null,
            "repository_sources": [
                "CRAN"
            ]
        }
    ],
    "dependencies_for_version": "1.3.0",
    "dependencies": [
        {
            "project_name": "withr",
            "name": "withr",
            "platform": "CRAN",
            "requirements": "*",
            "latest_stable": "2.4.0",
            "latest": "2.4.0",
            "deprecated": false,
            "outdated": false,
            "filepath": null,
            "kind": "suggests",
            "normalized_licenses": [
                "MIT"
            ]
        },
        {
            "project_name": "testthat",
            "name": "testthat",
            "platform": "CRAN",
            "requirements": ">= 2.3.2",
            "latest_stable": "3.0.4",
            "latest": "3.0.4",
            "deprecated": false,
            "outdated": false,
            "filepath": null,
            "kind": "suggests",
            "normalized_licenses": [
                "MIT"
            ]
        },
        {
            "project_name": "spelling",
            "name": "spelling",
            "platform": "CRAN",
            "requirements": "*",
            "latest_stable": null,
            "latest": "2.1",
            "deprecated": false,
            "outdated": null,
            "filepath": null,
            "kind": "suggests",
            "normalized_licenses": [
                "MIT"
            ]
        },
        {
            "project_name": "rprojroot",
            "name": "rprojroot",
            "platform": "CRAN",
            "requirements": "*",
            "latest_stable": "2.0.3",
            "latest": "2.0.3",
            "deprecated": false,
            "outdated": false,
            "filepath": null,
            "kind": "suggests",
            "normalized_licenses": [
                "MIT"
            ]
        },
        {
            "project_name": "rmarkdown",
            "name": "rmarkdown",
            "platform": "CRAN",
            "requirements": "*",
            "latest_stable": "0.9.6",
            "latest": "2.13",
            "deprecated": false,
            "outdated": false,
            "filepath": null,
            "kind": "suggests",
            "normalized_licenses": [
                "GPL-3.0"
            ]
        },
        {
            "project_name": "mockery",
            "name": "mockery",
            "platform": "CRAN",
            "requirements": "*",
            "latest_stable": "0.4.3",
            "latest": "0.4.3",
            "deprecated": false,
            "outdated": false,
            "filepath": null,
            "kind": "suggests",
            "normalized_licenses": [
                "MIT"
            ]
        },
        {
            "project_name": "knitr",
            "name": "knitr",
            "platform": "CRAN",
            "requirements": "*",
            "latest_stable": "1.15.1",
            "latest": "1.38",
            "deprecated": false,
            "outdated": false,
            "filepath": null,
            "kind": "suggests",
            "normalized_licenses": [
                "CNRI-Python-GPL-Compatible",
                "CNRI-Python-GPL-Compatible"
            ]
        },
        {
            "project_name": "covr",
            "name": "covr",
            "platform": "CRAN",
            "requirements": "*",
            "latest_stable": "3.5.1",
            "latest": "3.5.1",
            "deprecated": false,
            "outdated": false,
            "filepath": null,
            "kind": "suggests",
            "normalized_licenses": [
                "GPL-3.0"
            ]
        },
        {
            "project_name": "jsonlite",
            "name": "jsonlite",
            "platform": "CRAN",
            "requirements": "*",
            "latest_stable": "1.8.0",
            "latest": "1.8.0",
            "deprecated": false,
            "outdated": false,
            "filepath": null,
            "kind": "imports",
            "normalized_licenses": [
                "MIT"
            ]
        },
        {
            "project_name": "ini",
            "name": "ini",
            "platform": "CRAN",
            "requirements": "*",
            "latest_stable": "0.3.1",
            "latest": "0.3.1",
            "deprecated": false,
            "outdated": false,
            "filepath": null,
            "kind": "imports",
            "normalized_licenses": [
                "GPL-3.0"
            ]
        },
        {
            "project_name": "httr",
            "name": "httr",
            "platform": "CRAN",
            "requirements": ">= 1.2",
            "latest_stable": "1.4.2",
            "latest": "1.4.2",
            "deprecated": false,
            "outdated": false,
            "filepath": null,
            "kind": "imports",
            "normalized_licenses": [
                "MIT"
            ]
        },
        {
            "project_name": "gitcreds",
            "name": "gitcreds",
            "platform": "CRAN",
            "requirements": "*",
            "latest_stable": "0.1.1",
            "latest": "0.1.1",
            "deprecated": false,
            "outdated": false,
            "filepath": null,
            "kind": "imports",
            "normalized_licenses": [
                "MIT"
            ]
        },
        {
            "project_name": "cli",
            "name": "cli",
            "platform": "CRAN",
            "requirements": ">= 2.0.1",
            "latest_stable": "3.2.0",
            "latest": "3.2.0",
            "deprecated": false,
            "outdated": false,
            "filepath": null,
            "kind": "imports",
            "normalized_licenses": [
                "MIT"
            ]
        }
    ]
}