{
    "dependent_repos_count": 79,
    "dependents_count": 37,
    "deprecation_reason": null,
    "description": "A Toolbox for Non-Tabular Data Manipulation",
    "forks": 0,
    "homepage": "https://renkun.me/rlist",
    "keywords": [],
    "language": null,
    "latest_download_url": "https://cran.r-project.org/src/contrib/rlist_0.4.6.1.tar.gz",
    "latest_release_number": "0.4.6.1",
    "latest_release_published_at": "2016-04-04T00:00:00.000Z",
    "latest_stable_release_number": "0.4.6",
    "latest_stable_release_published_at": "2016-03-06T00:00:00.000Z",
    "license_normalized": false,
    "licenses": "MIT + file LICENSE",
    "name": "rlist",
    "normalized_licenses": [
        "MIT"
    ],
    "package_manager_url": "https://cran.r-project.org/package=rlist",
    "platform": "CRAN",
    "rank": 10,
    "repository_license": null,
    "repository_url": null,
    "stars": 0,
    "status": null,
    "versions": [
        {
            "number": "0.1",
            "published_at": "2014-06-27T06:55:00.000Z",
            "spdx_expression": null,
            "original_license": null,
            "researched_at": null,
            "repository_sources": [
                "CRAN"
            ]
        },
        {
            "number": "0.2.1",
            "published_at": "2014-07-04T13:39:00.000Z",
            "spdx_expression": null,
            "original_license": null,
            "researched_at": null,
            "repository_sources": [
                "CRAN"
            ]
        },
        {
            "number": "0.2.2",
            "published_at": "2014-07-11T06:48:00.000Z",
            "spdx_expression": null,
            "original_license": null,
            "researched_at": null,
            "repository_sources": [
                "CRAN"
            ]
        },
        {
            "number": "0.2.3",
            "published_at": "2014-07-18T07:09:00.000Z",
            "spdx_expression": null,
            "original_license": null,
            "researched_at": null,
            "repository_sources": [
                "CRAN"
            ]
        },
        {
            "number": "0.2.4",
            "published_at": "2014-07-26T11:04:00.000Z",
            "spdx_expression": null,
            "original_license": null,
            "researched_at": null,
            "repository_sources": [
                "CRAN"
            ]
        },
        {
            "number": "0.2.5",
            "published_at": "2014-08-01T01:31:00.000Z",
            "spdx_expression": null,
            "original_license": null,
            "researched_at": null,
            "repository_sources": [
                "CRAN"
            ]
        },
        {
            "number": "0.3",
            "published_at": "2014-08-07T20:31:00.000Z",
            "spdx_expression": null,
            "original_license": null,
            "researched_at": null,
            "repository_sources": [
                "CRAN"
            ]
        },
        {
            "number": "0.3-1",
            "published_at": "2014-08-15T16:50:00.000Z",
            "spdx_expression": null,
            "original_license": null,
            "researched_at": null,
            "repository_sources": [
                "CRAN"
            ]
        },
        {
            "number": "0.3-2",
            "published_at": "2014-08-22T07:17:00.000Z",
            "spdx_expression": null,
            "original_license": null,
            "researched_at": null,
            "repository_sources": [
                "CRAN"
            ]
        },
        {
            "number": "0.4",
            "published_at": "2015-01-24T00:00:00.000Z",
            "spdx_expression": null,
            "original_license": null,
            "researched_at": null,
            "repository_sources": [
                "CRAN"
            ]
        },
        {
            "number": "0.4.2.3",
            "published_at": "2015-07-09T00:00:00.000Z",
            "spdx_expression": null,
            "original_license": null,
            "researched_at": null,
            "repository_sources": [
                "CRAN"
            ]
        },
        {
            "number": "0.4.5.1",
            "published_at": "2015-09-09T00:00:00.000Z",
            "spdx_expression": null,
            "original_license": null,
            "researched_at": null,
            "repository_sources": [
                "CRAN"
            ]
        },
        {
            "number": "0.4.6",
            "published_at": "2016-03-06T00:00:00.000Z",
            "spdx_expression": null,
            "original_license": null,
            "researched_at": null,
            "repository_sources": [
                "CRAN"
            ]
        },
        {
            "number": "0.4.6.1",
            "published_at": "2016-04-04T00:00:00.000Z",
            "spdx_expression": null,
            "original_license": null,
            "researched_at": null,
            "repository_sources": [
                "CRAN"
            ]
        }
    ],
    "dependencies_for_version": "0.4.6.1",
    "dependencies": [
        {
            "project_name": "data.table",
            "name": "data.table",
            "platform": "CRAN",
            "requirements": "*",
            "latest_stable": "1.14.2",
            "latest": "1.14.2",
            "deprecated": false,
            "outdated": false,
            "filepath": null,
            "kind": "imports",
            "normalized_licenses": [
                "AML"
            ]
        },
        {
            "project_name": "jsonlite",
            "name": "jsonlite",
            "platform": "CRAN",
            "requirements": "*",
            "latest_stable": "1.8.0",
            "latest": "1.8.0",
            "deprecated": false,
            "outdated": false,
            "filepath": null,
            "kind": "imports",
            "normalized_licenses": [
                "MIT"
            ]
        },
        {
            "project_name": "testthat",
            "name": "testthat",
            "platform": "CRAN",
            "requirements": "*",
            "latest_stable": "3.0.4",
            "latest": "3.0.4",
            "deprecated": false,
            "outdated": false,
            "filepath": null,
            "kind": "suggests",
            "normalized_licenses": [
                "MIT"
            ]
        },
        {
            "project_name": "R",
            "name": "R",
            "platform": "CRAN",
            "requirements": ">= 2.15",
            "latest_stable": null,
            "latest": null,
            "deprecated": null,
            "outdated": null,
            "filepath": null,
            "kind": "depends",
            "normalized_licenses": null
        },
        {
            "project_name": "yaml",
            "name": "yaml",
            "platform": "CRAN",
            "requirements": "*",
            "latest_stable": "2.2.2",
            "latest": "2.2.2",
            "deprecated": false,
            "outdated": false,
            "filepath": null,
            "kind": "imports",
            "normalized_licenses": [
                "BSD-1-Clause"
            ]
        },
        {
            "project_name": "XML",
            "name": "XML",
            "platform": "CRAN",
            "requirements": "*",
            "latest_stable": null,
            "latest": "3.99-0.9",
            "deprecated": false,
            "outdated": null,
            "filepath": null,
            "kind": "imports",
            "normalized_licenses": [
                "BSD-1-Clause"
            ]
        }
    ]
}