{
    "dependent_repos_count": 217708,
    "dependents_count": 234,
    "deprecation_reason": null,
    "description": "Custom error messages in JSON Schemas for Ajv validator",
    "forks": 13,
    "homepage": "https://github.com/epoberezkin/ajv-errors#readme",
    "keywords": [
        "ajv",
        "json-schema",
        "validator",
        "error",
        "messages",
        "errors"
    ],
    "language": "TypeScript",
    "latest_download_url": "https://registry.npmjs.org/ajv-errors/-/ajv-errors-3.0.0.tgz",
    "latest_release_number": "3.0.0",
    "latest_release_published_at": "2021-03-27T22:58:27.086Z",
    "latest_stable_release_number": "3.0.0",
    "latest_stable_release_published_at": "2021-03-27T22:58:27.086Z",
    "license_normalized": false,
    "licenses": "MIT",
    "name": "ajv-errors",
    "normalized_licenses": [
        "MIT"
    ],
    "package_manager_url": "https://www.npmjs.com/package/ajv-errors",
    "platform": "NPM",
    "rank": 22,
    "repository_license": "MIT",
    "repository_url": "https://github.com/epoberezkin/ajv-errors",
    "stars": 185,
    "status": null,
    "versions": [
        {
            "number": "0.0.1",
            "published_at": "2017-03-05T11:40:42.016Z",
            "spdx_expression": "MIT",
            "original_license": "MIT",
            "researched_at": null,
            "repository_sources": [
                "NPM"
            ]
        },
        {
            "number": "0.1.0",
            "published_at": "2017-04-30T18:47:58.032Z",
            "spdx_expression": "MIT",
            "original_license": "MIT",
            "researched_at": null,
            "repository_sources": [
                "NPM"
            ]
        },
        {
            "number": "0.1.1",
            "published_at": "2017-04-30T19:36:45.272Z",
            "spdx_expression": "MIT",
            "original_license": "MIT",
            "researched_at": null,
            "repository_sources": [
                "NPM"
            ]
        },
        {
            "number": "0.1.2",
            "published_at": "2017-04-30T20:24:16.937Z",
            "spdx_expression": "MIT",
            "original_license": "MIT",
            "researched_at": null,
            "repository_sources": [
                "NPM"
            ]
        },
        {
            "number": "0.2.0",
            "published_at": "2017-05-01T16:32:10.431Z",
            "spdx_expression": "MIT",
            "original_license": "MIT",
            "researched_at": null,
            "repository_sources": [
                "NPM"
            ]
        },
        {
            "number": "0.3.0",
            "published_at": "2017-05-09T19:14:33.951Z",
            "spdx_expression": "MIT",
            "original_license": "MIT",
            "researched_at": null,
            "repository_sources": [
                "NPM"
            ]
        },
        {
            "number": "0.4.0",
            "published_at": "2017-05-09T21:46:40.263Z",
            "spdx_expression": "MIT",
            "original_license": "MIT",
            "researched_at": null,
            "repository_sources": [
                "NPM"
            ]
        },
        {
            "number": "0.5.0",
            "published_at": "2017-05-27T15:34:53.768Z",
            "spdx_expression": "MIT",
            "original_license": "MIT",
            "researched_at": null,
            "repository_sources": [
                "NPM"
            ]
        },
        {
            "number": "1.0.0",
            "published_at": "2017-05-27T17:59:41.038Z",
            "spdx_expression": "MIT",
            "original_license": "MIT",
            "researched_at": null,
            "repository_sources": [
                "NPM"
            ]
        },
        {
            "number": "1.0.1",
            "published_at": "2018-12-09T20:44:23.016Z",
            "spdx_expression": "MIT",
            "original_license": "MIT",
            "researched_at": null,
            "repository_sources": [
                "NPM"
            ]
        },
        {
            "number": "2.0.0",
            "published_at": "2020-12-15T21:01:17.375Z",
            "spdx_expression": "MIT",
            "original_license": "MIT",
            "researched_at": null,
            "repository_sources": [
                "NPM"
            ]
        },
        {
            "number": "2.0.0-beta.0",
            "published_at": "2020-11-22T13:04:13.703Z",
            "spdx_expression": "MIT",
            "original_license": "MIT",
            "researched_at": null,
            "repository_sources": [
                "NPM"
            ]
        },
        {
            "number": "2.0.1",
            "published_at": "2021-03-10T21:17:23.906Z",
            "spdx_expression": "MIT",
            "original_license": "MIT",
            "researched_at": null,
            "repository_sources": [
                "NPM"
            ]
        },
        {
            "number": "3.0.0",
            "published_at": "2021-03-27T22:58:27.086Z",
            "spdx_expression": "MIT",
            "original_license": "MIT",
            "researched_at": null,
            "repository_sources": [
                "NPM"
            ]
        }
    ],
    "dependencies_for_version": "3.0.0",
    "dependencies": []
}