{
    "dependent_repos_count": 0,
    "dependents_count": 0,
    "deprecation_reason": null,
    "description": "Aerocapture Mission Analysis Tool",
    "forks": 0,
    "homepage": "https://github.com/athulpg007/AMAT",
    "keywords": [],
    "language": "Python",
    "latest_download_url": null,
    "latest_release_number": "2.2.5",
    "latest_release_published_at": "2022-02-12T19:18:50.000Z",
    "latest_stable_release_number": "2.2.5",
    "latest_stable_release_published_at": "2022-02-12T19:18:50.000Z",
    "license_normalized": true,
    "licenses": "GPL-3.0-or-later",
    "name": "AMAT",
    "normalized_licenses": [
        "CNRI-Python-GPL-Compatible"
    ],
    "package_manager_url": "https://pypi.org/project/AMAT/",
    "platform": "Pypi",
    "rank": 9,
    "repository_license": "Other",
    "repository_url": "https://github.com/athulpg007/AMAT",
    "stars": 8,
    "status": null,
    "versions": [
        {
            "number": "0.0.1.dev1",
            "published_at": "2019-10-25T18:21:14.000Z",
            "spdx_expression": null,
            "original_license": null,
            "researched_at": null,
            "repository_sources": [
                "Pypi"
            ]
        },
        {
            "number": "1.0",
            "published_at": "2020-03-05T07:50:02.000Z",
            "spdx_expression": null,
            "original_license": null,
            "researched_at": null,
            "repository_sources": [
                "Pypi"
            ]
        },
        {
            "number": "1.0.1",
            "published_at": "2020-03-05T07:54:12.000Z",
            "spdx_expression": null,
            "original_license": null,
            "researched_at": null,
            "repository_sources": [
                "Pypi"
            ]
        },
        {
            "number": "2.0",
            "published_at": "2020-03-05T20:18:22.000Z",
            "spdx_expression": null,
            "original_license": null,
            "researched_at": null,
            "repository_sources": [
                "Pypi"
            ]
        },
        {
            "number": "1.0.3",
            "published_at": "2020-03-06T03:38:03.000Z",
            "spdx_expression": null,
            "original_license": null,
            "researched_at": null,
            "repository_sources": [
                "Pypi"
            ]
        },
        {
            "number": "2.0.1",
            "published_at": "2020-03-06T03:39:53.000Z",
            "spdx_expression": null,
            "original_license": null,
            "researched_at": null,
            "repository_sources": [
                "Pypi"
            ]
        },
        {
            "number": "2.0.2",
            "published_at": "2020-03-13T05:14:15.000Z",
            "spdx_expression": null,
            "original_license": null,
            "researched_at": null,
            "repository_sources": [
                "Pypi"
            ]
        },
        {
            "number": "2.0.3",
            "published_at": "2020-03-13T05:24:37.000Z",
            "spdx_expression": null,
            "original_license": null,
            "researched_at": null,
            "repository_sources": [
                "Pypi"
            ]
        },
        {
            "number": "2.0.4",
            "published_at": "2020-03-16T19:50:32.000Z",
            "spdx_expression": null,
            "original_license": null,
            "researched_at": null,
            "repository_sources": [
                "Pypi"
            ]
        },
        {
            "number": "2.0.5",
            "published_at": "2020-03-19T04:32:30.000Z",
            "spdx_expression": null,
            "original_license": null,
            "researched_at": null,
            "repository_sources": [
                "Pypi"
            ]
        },
        {
            "number": "2.0.8",
            "published_at": "2020-06-29T12:49:36.000Z",
            "spdx_expression": "NOASSERTION",
            "original_license": "cc-by-sa-4.0",
            "researched_at": null,
            "repository_sources": [
                "Pypi"
            ]
        },
        {
            "number": "2.0.9",
            "published_at": "2020-07-13T02:54:13.000Z",
            "spdx_expression": "NOASSERTION",
            "original_license": "cc-by-sa-4.0",
            "researched_at": null,
            "repository_sources": [
                "Pypi"
            ]
        },
        {
            "number": "2.1.0",
            "published_at": "2020-07-15T01:12:01.000Z",
            "spdx_expression": "NOASSERTION",
            "original_license": "cc-by-sa-4.0",
            "researched_at": null,
            "repository_sources": [
                "Pypi"
            ]
        },
        {
            "number": "2.1.1",
            "published_at": "2020-07-19T18:49:12.000Z",
            "spdx_expression": "NOASSERTION",
            "original_license": "cc-by-sa-4.0",
            "researched_at": null,
            "repository_sources": [
                "Pypi"
            ]
        },
        {
            "number": "2.1.2",
            "published_at": "2020-07-30T00:30:50.000Z",
            "spdx_expression": "NOASSERTION",
            "original_license": "cc-by-sa-4.0",
            "researched_at": null,
            "repository_sources": [
                "Pypi"
            ]
        },
        {
            "number": "2.1.3",
            "published_at": "2020-07-31T02:53:47.000Z",
            "spdx_expression": "NOASSERTION",
            "original_license": "cc-by-sa-4.0",
            "researched_at": null,
            "repository_sources": [
                "Pypi"
            ]
        },
        {
            "number": "2.1.4",
            "published_at": "2021-07-31T17:32:19.000Z",
            "spdx_expression": "NOASSERTION",
            "original_license": "cc-by-sa-4.0",
            "researched_at": null,
            "repository_sources": [
                "Pypi"
            ]
        },
        {
            "number": "2.1.5",
            "published_at": "2021-07-31T19:28:11.000Z",
            "spdx_expression": "NOASSERTION",
            "original_license": "cc-by-sa-4.0",
            "researched_at": null,
            "repository_sources": [
                "Pypi"
            ]
        },
        {
            "number": "2.1.7",
            "published_at": "2021-07-31T19:41:28.000Z",
            "spdx_expression": "NOASSERTION",
            "original_license": "cc-by-sa-4.0",
            "researched_at": null,
            "repository_sources": [
                "Pypi"
            ]
        },
        {
            "number": "2.1.8",
            "published_at": "2021-07-31T19:58:46.000Z",
            "spdx_expression": "NOASSERTION",
            "original_license": "cc-by-sa-4.0",
            "researched_at": null,
            "repository_sources": [
                "Pypi"
            ]
        },
        {
            "number": "2.1.10",
            "published_at": "2021-09-11T16:48:49.000Z",
            "spdx_expression": "GPL-3.0-or-later",
            "original_license": "GPL-3.0-or-later",
            "researched_at": null,
            "repository_sources": [
                "Pypi"
            ]
        },
        {
            "number": "2.1.9",
            "published_at": "2021-09-11T15:33:33.000Z",
            "spdx_expression": "NOASSERTION",
            "original_license": "cc-by-sa-4.0",
            "researched_at": null,
            "repository_sources": [
                "Pypi"
            ]
        },
        {
            "number": "2.1.11",
            "published_at": "2021-09-18T23:47:59.000Z",
            "spdx_expression": "GPL-3.0-or-later",
            "original_license": "GPL-3.0-or-later",
            "researched_at": null,
            "repository_sources": [
                "Pypi"
            ]
        },
        {
            "number": "2.2.1",
            "published_at": "2021-11-04T03:26:04.000Z",
            "spdx_expression": "GPL-3.0-or-later",
            "original_license": "GPL-3.0-or-later",
            "researched_at": null,
            "repository_sources": [
                "Pypi"
            ]
        },
        {
            "number": "2.2.3",
            "published_at": "2021-11-05T23:55:36.000Z",
            "spdx_expression": "GPL-3.0-or-later",
            "original_license": "GPL-3.0-or-later",
            "researched_at": null,
            "repository_sources": [
                "Pypi"
            ]
        },
        {
            "number": "2.2.5",
            "published_at": "2022-02-12T19:18:50.000Z",
            "spdx_expression": "GPL-3.0-or-later",
            "original_license": "GPL-3.0-or-later",
            "researched_at": null,
            "repository_sources": [
                "Pypi"
            ]
        }
    ]
}