{
    "dependent_repos_count": 10,
    "dependents_count": 8,
    "deprecation_reason": null,
    "description": "32-Bit Floats",
    "forks": 9,
    "homepage": "https://github.com/wrathematics/float",
    "keywords": [
        "float-matrix",
        "hpc",
        "linear-algebra",
        "matrix",
        "r"
    ],
    "language": "Fortran",
    "latest_download_url": "https://cran.r-project.org/src/contrib/float_0.3-0.tar.gz",
    "latest_release_number": "0.3-0",
    "latest_release_published_at": "2022-04-07T00:00:00.000Z",
    "latest_stable_release_number": null,
    "latest_stable_release_published_at": null,
    "license_normalized": true,
    "licenses": "BSD 2-clause License + file LICENSE",
    "name": "float",
    "normalized_licenses": [
        "BSD-1-Clause"
    ],
    "package_manager_url": "https://cran.r-project.org/package=float",
    "platform": "CRAN",
    "rank": 13,
    "repository_license": "Other",
    "repository_url": "https://github.com/wrathematics/float",
    "stars": 42,
    "status": null,
    "versions": [
        {
            "number": "0.1-1",
            "published_at": "2017-11-30T11:19:00.000Z",
            "spdx_expression": null,
            "original_license": null,
            "researched_at": null,
            "repository_sources": [
                "CRAN"
            ]
        },
        {
            "number": "0.2-0",
            "published_at": "2018-08-06T15:00:00.000Z",
            "spdx_expression": null,
            "original_license": null,
            "researched_at": null,
            "repository_sources": [
                "CRAN"
            ]
        },
        {
            "number": "0.2-1",
            "published_at": "2018-12-07T12:40:00.000Z",
            "spdx_expression": null,
            "original_license": null,
            "researched_at": null,
            "repository_sources": [
                "CRAN"
            ]
        },
        {
            "number": "0.2-2",
            "published_at": "2019-02-26T13:50:00.000Z",
            "spdx_expression": null,
            "original_license": null,
            "researched_at": null,
            "repository_sources": [
                "CRAN"
            ]
        },
        {
            "number": "0.2-3",
            "published_at": "2019-05-31T06:40:00.000Z",
            "spdx_expression": null,
            "original_license": null,
            "researched_at": null,
            "repository_sources": [
                "CRAN"
            ]
        },
        {
            "number": "0.2-4",
            "published_at": "2020-04-22T16:42:00.000Z",
            "spdx_expression": null,
            "original_license": null,
            "researched_at": null,
            "repository_sources": [
                "CRAN"
            ]
        },
        {
            "number": "0.2-6",
            "published_at": "2021-09-20T14:50:00.000Z",
            "spdx_expression": null,
            "original_license": null,
            "researched_at": null,
            "repository_sources": [
                "CRAN"
            ]
        },
        {
            "number": "0.2-6.1",
            "published_at": "2022-03-14T06:19:00.000Z",
            "spdx_expression": null,
            "original_license": null,
            "researched_at": null,
            "repository_sources": [
                "CRAN"
            ]
        },
        {
            "number": "0.3-0",
            "published_at": "2022-04-07T00:00:00.000Z",
            "spdx_expression": null,
            "original_license": null,
            "researched_at": null,
            "repository_sources": [
                "CRAN"
            ]
        }
    ]
}